{
  "id": "2f32db3c-7a8a-49c2-b538-b6375f49342d",
  "prevId": "47930b33-7f2c-424c-9d62-ea17a1965279",
  "version": "7",
  "dialect": "postgresql",
  "tables": {
    "public.alerts": {
      "name": "alerts",
      "schema": "",
      "columns": {
        "id": {
          "name": "id",
          "type": "integer",
          "primaryKey": true,
          "notNull": true,
          "identity": {
            "type": "always",
            "name": "alerts_id_seq",
            "schema": "public",
            "increment": "1",
            "startWith": "1",
            "minValue": "1",
            "maxValue": "2147483647",
            "cache": "1",
            "cycle": false
          }
        },
        "severity": {
          "name": "severity",
          "type": "alert_severity",
          "typeSchema": "public",
          "primaryKey": false,
          "notNull": true,
          "default": "'info'"
        },
        "status": {
          "name": "status",
          "type": "alert_status",
          "typeSchema": "public",
          "primaryKey": false,
          "notNull": true,
          "default": "'pending'"
        },
        "alert_type": {
          "name": "alert_type",
          "type": "varchar(50)",
          "primaryKey": false,
          "notNull": true
        },
        "message": {
          "name": "message",
          "type": "text",
          "primaryKey": false,
          "notNull": true
        },
        "budget_id": {
          "name": "budget_id",
          "type": "integer",
          "primaryKey": false,
          "notNull": false
        },
        "whatsapp_message_id": {
          "name": "whatsapp_message_id",
          "type": "varchar(255)",
          "primaryKey": false,
          "notNull": false
        },
        "is_active": {
          "name": "is_active",
          "type": "boolean",
          "primaryKey": false,
          "notNull": true,
          "default": true
        },
        "created_at": {
          "name": "created_at",
          "type": "timestamp",
          "primaryKey": false,
          "notNull": true,
          "default": "now()"
        },
        "resolved_at": {
          "name": "resolved_at",
          "type": "timestamp",
          "primaryKey": false,
          "notNull": false
        },
        "deleted_at": {
          "name": "deleted_at",
          "type": "timestamp",
          "primaryKey": false,
          "notNull": false
        }
      },
      "indexes": {
        "idx_alerts_type_created": {
          "name": "idx_alerts_type_created",
          "columns": [
            {
              "expression": "alert_type",
              "isExpression": false,
              "asc": true,
              "nulls": "last"
            },
            {
              "expression": "created_at",
              "isExpression": false,
              "asc": true,
              "nulls": "last"
            }
          ],
          "isUnique": false,
          "concurrently": false,
          "method": "btree",
          "with": {}
        },
        "idx_alerts_active_created": {
          "name": "idx_alerts_active_created",
          "columns": [
            {
              "expression": "is_active",
              "isExpression": false,
              "asc": true,
              "nulls": "last"
            },
            {
              "expression": "created_at",
              "isExpression": false,
              "asc": true,
              "nulls": "last"
            }
          ],
          "isUnique": false,
          "concurrently": false,
          "method": "btree",
          "with": {}
        }
      },
      "foreignKeys": {
        "alerts_budget_id_budgets_id_fk": {
          "name": "alerts_budget_id_budgets_id_fk",
          "tableFrom": "alerts",
          "tableTo": "budgets",
          "columnsFrom": [
            "budget_id"
          ],
          "columnsTo": [
            "id"
          ],
          "onDelete": "no action",
          "onUpdate": "no action"
        }
      },
      "compositePrimaryKeys": {},
      "uniqueConstraints": {},
      "policies": {},
      "checkConstraints": {},
      "isRLSEnabled": false
    },
    "public.app_settings": {
      "name": "app_settings",
      "schema": "",
      "columns": {
        "key": {
          "name": "key",
          "type": "text",
          "primaryKey": true,
          "notNull": true
        },
        "value": {
          "name": "value",
          "type": "jsonb",
          "primaryKey": false,
          "notNull": true
        },
        "updated_at": {
          "name": "updated_at",
          "type": "timestamp with time zone",
          "primaryKey": false,
          "notNull": true,
          "default": "now()"
        }
      },
      "indexes": {},
      "foreignKeys": {},
      "compositePrimaryKeys": {},
      "uniqueConstraints": {},
      "policies": {},
      "checkConstraints": {},
      "isRLSEnabled": false
    },
    "public.audit_log": {
      "name": "audit_log",
      "schema": "",
      "columns": {
        "id": {
          "name": "id",
          "type": "integer",
          "primaryKey": true,
          "notNull": true,
          "identity": {
            "type": "always",
            "name": "audit_log_id_seq",
            "schema": "public",
            "increment": "1",
            "startWith": "1",
            "minValue": "1",
            "maxValue": "2147483647",
            "cache": "1",
            "cycle": false
          }
        },
        "action": {
          "name": "action",
          "type": "varchar(100)",
          "primaryKey": false,
          "notNull": true
        },
        "entity_type": {
          "name": "entity_type",
          "type": "varchar(50)",
          "primaryKey": false,
          "notNull": true
        },
        "entity_id": {
          "name": "entity_id",
          "type": "integer",
          "primaryKey": false,
          "notNull": false
        },
        "actor_type": {
          "name": "actor_type",
          "type": "actor_type",
          "typeSchema": "public",
          "primaryKey": false,
          "notNull": true,
          "default": "'system'"
        },
        "details": {
          "name": "details",
          "type": "jsonb",
          "primaryKey": false,
          "notNull": false
        },
        "created_at": {
          "name": "created_at",
          "type": "timestamp",
          "primaryKey": false,
          "notNull": true,
          "default": "now()"
        }
      },
      "indexes": {},
      "foreignKeys": {},
      "compositePrimaryKeys": {},
      "uniqueConstraints": {},
      "policies": {},
      "checkConstraints": {},
      "isRLSEnabled": false
    },
    "public.budgets": {
      "name": "budgets",
      "schema": "",
      "columns": {
        "id": {
          "name": "id",
          "type": "integer",
          "primaryKey": true,
          "notNull": true,
          "identity": {
            "type": "always",
            "name": "budgets_id_seq",
            "schema": "public",
            "increment": "1",
            "startWith": "1",
            "minValue": "1",
            "maxValue": "2147483647",
            "cache": "1",
            "cycle": false
          }
        },
        "name": {
          "name": "name",
          "type": "varchar(100)",
          "primaryKey": false,
          "notNull": true
        },
        "platform_id": {
          "name": "platform_id",
          "type": "integer",
          "primaryKey": false,
          "notNull": false
        },
        "project_id": {
          "name": "project_id",
          "type": "integer",
          "primaryKey": false,
          "notNull": false
        },
        "monthly_limit": {
          "name": "monthly_limit",
          "type": "numeric(10, 2)",
          "primaryKey": false,
          "notNull": true
        },
        "alert_at_50": {
          "name": "alert_at_50",
          "type": "boolean",
          "primaryKey": false,
          "notNull": true,
          "default": true
        },
        "alert_at_75": {
          "name": "alert_at_75",
          "type": "boolean",
          "primaryKey": false,
          "notNull": true,
          "default": true
        },
        "alert_at_90": {
          "name": "alert_at_90",
          "type": "boolean",
          "primaryKey": false,
          "notNull": true,
          "default": true
        },
        "alert_at_100": {
          "name": "alert_at_100",
          "type": "boolean",
          "primaryKey": false,
          "notNull": true,
          "default": true
        },
        "is_active": {
          "name": "is_active",
          "type": "boolean",
          "primaryKey": false,
          "notNull": true,
          "default": true
        },
        "created_at": {
          "name": "created_at",
          "type": "timestamp",
          "primaryKey": false,
          "notNull": true,
          "default": "now()"
        },
        "deleted_at": {
          "name": "deleted_at",
          "type": "timestamp",
          "primaryKey": false,
          "notNull": false
        }
      },
      "indexes": {},
      "foreignKeys": {
        "budgets_platform_id_platforms_id_fk": {
          "name": "budgets_platform_id_platforms_id_fk",
          "tableFrom": "budgets",
          "tableTo": "platforms",
          "columnsFrom": [
            "platform_id"
          ],
          "columnsTo": [
            "id"
          ],
          "onDelete": "no action",
          "onUpdate": "no action"
        },
        "budgets_project_id_projects_id_fk": {
          "name": "budgets_project_id_projects_id_fk",
          "tableFrom": "budgets",
          "tableTo": "projects",
          "columnsFrom": [
            "project_id"
          ],
          "columnsTo": [
            "id"
          ],
          "onDelete": "no action",
          "onUpdate": "no action"
        }
      },
      "compositePrimaryKeys": {},
      "uniqueConstraints": {},
      "policies": {},
      "checkConstraints": {},
      "isRLSEnabled": false
    },
    "public.collection_runs": {
      "name": "collection_runs",
      "schema": "",
      "columns": {
        "id": {
          "name": "id",
          "type": "integer",
          "primaryKey": true,
          "notNull": true,
          "identity": {
            "type": "always",
            "name": "collection_runs_id_seq",
            "schema": "public",
            "increment": "1",
            "startWith": "1",
            "minValue": "1",
            "maxValue": "2147483647",
            "cache": "1",
            "cycle": false
          }
        },
        "platform_id": {
          "name": "platform_id",
          "type": "integer",
          "primaryKey": false,
          "notNull": true
        },
        "trigger_type": {
          "name": "trigger_type",
          "type": "varchar(20)",
          "primaryKey": false,
          "notNull": true,
          "default": "'manual'"
        },
        "status": {
          "name": "status",
          "type": "collection_run_status",
          "typeSchema": "public",
          "primaryKey": false,
          "notNull": true,
          "default": "'running'"
        },
        "records_collected": {
          "name": "records_collected",
          "type": "integer",
          "primaryKey": false,
          "notNull": false,
          "default": 0
        },
        "error_message": {
          "name": "error_message",
          "type": "text",
          "primaryKey": false,
          "notNull": false
        },
        "started_at": {
          "name": "started_at",
          "type": "timestamp",
          "primaryKey": false,
          "notNull": true,
          "default": "now()"
        },
        "completed_at": {
          "name": "completed_at",
          "type": "timestamp",
          "primaryKey": false,
          "notNull": false
        }
      },
      "indexes": {
        "idx_collection_runs_platform_started": {
          "name": "idx_collection_runs_platform_started",
          "columns": [
            {
              "expression": "platform_id",
              "isExpression": false,
              "asc": true,
              "nulls": "last"
            },
            {
              "expression": "started_at",
              "isExpression": false,
              "asc": true,
              "nulls": "last"
            }
          ],
          "isUnique": false,
          "concurrently": false,
          "method": "btree",
          "with": {}
        }
      },
      "foreignKeys": {
        "collection_runs_platform_id_platforms_id_fk": {
          "name": "collection_runs_platform_id_platforms_id_fk",
          "tableFrom": "collection_runs",
          "tableTo": "platforms",
          "columnsFrom": [
            "platform_id"
          ],
          "columnsTo": [
            "id"
          ],
          "onDelete": "no action",
          "onUpdate": "no action"
        }
      },
      "compositePrimaryKeys": {},
      "uniqueConstraints": {},
      "policies": {},
      "checkConstraints": {},
      "isRLSEnabled": false
    },
    "public.cost_attribution_weights": {
      "name": "cost_attribution_weights",
      "schema": "",
      "columns": {
        "id": {
          "name": "id",
          "type": "integer",
          "primaryKey": true,
          "notNull": true,
          "identity": {
            "type": "always",
            "name": "cost_attribution_weights_id_seq",
            "schema": "public",
            "increment": "1",
            "startWith": "1",
            "minValue": "1",
            "maxValue": "2147483647",
            "cache": "1",
            "cycle": false
          }
        },
        "platform_id": {
          "name": "platform_id",
          "type": "integer",
          "primaryKey": false,
          "notNull": true
        },
        "project_slug": {
          "name": "project_slug",
          "type": "varchar(100)",
          "primaryKey": false,
          "notNull": true
        },
        "weight": {
          "name": "weight",
          "type": "numeric(6, 4)",
          "primaryKey": false,
          "notNull": true
        },
        "basis": {
          "name": "basis",
          "type": "varchar(50)",
          "primaryKey": false,
          "notNull": true,
          "default": "'manual'"
        },
        "updated_at": {
          "name": "updated_at",
          "type": "timestamp",
          "primaryKey": false,
          "notNull": true,
          "default": "now()"
        },
        "created_at": {
          "name": "created_at",
          "type": "timestamp",
          "primaryKey": false,
          "notNull": true,
          "default": "now()"
        }
      },
      "indexes": {
        "idx_attr_weights_platform": {
          "name": "idx_attr_weights_platform",
          "columns": [
            {
              "expression": "platform_id",
              "isExpression": false,
              "asc": true,
              "nulls": "last"
            }
          ],
          "isUnique": false,
          "concurrently": false,
          "method": "btree",
          "with": {}
        }
      },
      "foreignKeys": {
        "cost_attribution_weights_platform_id_platforms_id_fk": {
          "name": "cost_attribution_weights_platform_id_platforms_id_fk",
          "tableFrom": "cost_attribution_weights",
          "tableTo": "platforms",
          "columnsFrom": [
            "platform_id"
          ],
          "columnsTo": [
            "id"
          ],
          "onDelete": "no action",
          "onUpdate": "no action"
        }
      },
      "compositePrimaryKeys": {},
      "uniqueConstraints": {},
      "policies": {},
      "checkConstraints": {},
      "isRLSEnabled": false
    },
    "public.cost_records": {
      "name": "cost_records",
      "schema": "",
      "columns": {
        "id": {
          "name": "id",
          "type": "integer",
          "primaryKey": true,
          "notNull": true,
          "identity": {
            "type": "always",
            "name": "cost_records_id_seq",
            "schema": "public",
            "increment": "1",
            "startWith": "1",
            "minValue": "1",
            "maxValue": "2147483647",
            "cache": "1",
            "cycle": false
          }
        },
        "platform_id": {
          "name": "platform_id",
          "type": "integer",
          "primaryKey": false,
          "notNull": true
        },
        "service_id": {
          "name": "service_id",
          "type": "integer",
          "primaryKey": false,
          "notNull": false
        },
        "invoice_id": {
          "name": "invoice_id",
          "type": "integer",
          "primaryKey": false,
          "notNull": false
        },
        "record_date": {
          "name": "record_date",
          "type": "timestamp",
          "primaryKey": false,
          "notNull": true
        },
        "period_start": {
          "name": "period_start",
          "type": "timestamp",
          "primaryKey": false,
          "notNull": true
        },
        "period_end": {
          "name": "period_end",
          "type": "timestamp",
          "primaryKey": false,
          "notNull": true
        },
        "amount": {
          "name": "amount",
          "type": "numeric(10, 4)",
          "primaryKey": false,
          "notNull": true
        },
        "currency": {
          "name": "currency",
          "type": "varchar(3)",
          "primaryKey": false,
          "notNull": true,
          "default": "'USD'"
        },
        "cost_type": {
          "name": "cost_type",
          "type": "cost_type",
          "typeSchema": "public",
          "primaryKey": false,
          "notNull": true,
          "default": "'usage'"
        },
        "collection_method": {
          "name": "collection_method",
          "type": "collection_method",
          "typeSchema": "public",
          "primaryKey": false,
          "notNull": true
        },
        "raw_data": {
          "name": "raw_data",
          "type": "jsonb",
          "primaryKey": false,
          "notNull": false
        },
        "notes": {
          "name": "notes",
          "type": "text",
          "primaryKey": false,
          "notNull": false
        },
        "is_active": {
          "name": "is_active",
          "type": "boolean",
          "primaryKey": false,
          "notNull": true,
          "default": true
        },
        "created_at": {
          "name": "created_at",
          "type": "timestamp",
          "primaryKey": false,
          "notNull": true,
          "default": "now()"
        },
        "deleted_at": {
          "name": "deleted_at",
          "type": "timestamp",
          "primaryKey": false,
          "notNull": false
        }
      },
      "indexes": {
        "idx_cost_records_platform": {
          "name": "idx_cost_records_platform",
          "columns": [
            {
              "expression": "platform_id",
              "isExpression": false,
              "asc": true,
              "nulls": "last"
            }
          ],
          "isUnique": false,
          "concurrently": false,
          "method": "btree",
          "with": {}
        },
        "idx_cost_records_period": {
          "name": "idx_cost_records_period",
          "columns": [
            {
              "expression": "period_start",
              "isExpression": false,
              "asc": true,
              "nulls": "last"
            },
            {
              "expression": "period_end",
              "isExpression": false,
              "asc": true,
              "nulls": "last"
            }
          ],
          "isUnique": false,
          "concurrently": false,
          "method": "btree",
          "with": {}
        },
        "idx_cost_records_platform_period": {
          "name": "idx_cost_records_platform_period",
          "columns": [
            {
              "expression": "platform_id",
              "isExpression": false,
              "asc": true,
              "nulls": "last"
            },
            {
              "expression": "period_start",
              "isExpression": false,
              "asc": true,
              "nulls": "last"
            },
            {
              "expression": "period_end",
              "isExpression": false,
              "asc": true,
              "nulls": "last"
            }
          ],
          "isUnique": false,
          "concurrently": false,
          "method": "btree",
          "with": {}
        },
        "idx_cost_records_record_date": {
          "name": "idx_cost_records_record_date",
          "columns": [
            {
              "expression": "record_date",
              "isExpression": false,
              "asc": true,
              "nulls": "last"
            }
          ],
          "isUnique": false,
          "concurrently": false,
          "method": "btree",
          "with": {}
        },
        "idx_cost_records_invoice": {
          "name": "idx_cost_records_invoice",
          "columns": [
            {
              "expression": "invoice_id",
              "isExpression": false,
              "asc": true,
              "nulls": "last"
            }
          ],
          "isUnique": false,
          "concurrently": false,
          "method": "btree",
          "with": {}
        }
      },
      "foreignKeys": {
        "cost_records_platform_id_platforms_id_fk": {
          "name": "cost_records_platform_id_platforms_id_fk",
          "tableFrom": "cost_records",
          "tableTo": "platforms",
          "columnsFrom": [
            "platform_id"
          ],
          "columnsTo": [
            "id"
          ],
          "onDelete": "no action",
          "onUpdate": "no action"
        },
        "cost_records_service_id_services_id_fk": {
          "name": "cost_records_service_id_services_id_fk",
          "tableFrom": "cost_records",
          "tableTo": "services",
          "columnsFrom": [
            "service_id"
          ],
          "columnsTo": [
            "id"
          ],
          "onDelete": "no action",
          "onUpdate": "no action"
        }
      },
      "compositePrimaryKeys": {},
      "uniqueConstraints": {},
      "policies": {},
      "checkConstraints": {},
      "isRLSEnabled": false
    },
    "public.credit_balances": {
      "name": "credit_balances",
      "schema": "",
      "columns": {
        "id": {
          "name": "id",
          "type": "integer",
          "primaryKey": true,
          "notNull": true,
          "identity": {
            "type": "always",
            "name": "credit_balances_id_seq",
            "schema": "public",
            "increment": "1",
            "startWith": "1",
            "minValue": "1",
            "maxValue": "2147483647",
            "cache": "1",
            "cycle": false
          }
        },
        "platform": {
          "name": "platform",
          "type": "varchar(50)",
          "primaryKey": false,
          "notNull": true
        },
        "balance": {
          "name": "balance",
          "type": "numeric(10, 4)",
          "primaryKey": false,
          "notNull": true
        },
        "updated_at": {
          "name": "updated_at",
          "type": "timestamp",
          "primaryKey": false,
          "notNull": true,
          "default": "now()"
        },
        "created_at": {
          "name": "created_at",
          "type": "timestamp",
          "primaryKey": false,
          "notNull": true,
          "default": "now()"
        }
      },
      "indexes": {},
      "foreignKeys": {},
      "compositePrimaryKeys": {},
      "uniqueConstraints": {
        "credit_balances_platform_unique": {
          "name": "credit_balances_platform_unique",
          "nullsNotDistinct": false,
          "columns": [
            "platform"
          ]
        }
      },
      "policies": {},
      "checkConstraints": {},
      "isRLSEnabled": false
    },
    "public.invoices": {
      "name": "invoices",
      "schema": "",
      "columns": {
        "id": {
          "name": "id",
          "type": "integer",
          "primaryKey": true,
          "notNull": true,
          "identity": {
            "type": "always",
            "name": "invoices_id_seq",
            "schema": "public",
            "increment": "1",
            "startWith": "1",
            "minValue": "1",
            "maxValue": "2147483647",
            "cache": "1",
            "cycle": false
          }
        },
        "platform_id": {
          "name": "platform_id",
          "type": "integer",
          "primaryKey": false,
          "notNull": true
        },
        "invoice_number": {
          "name": "invoice_number",
          "type": "varchar(100)",
          "primaryKey": false,
          "notNull": false
        },
        "invoice_date": {
          "name": "invoice_date",
          "type": "timestamp",
          "primaryKey": false,
          "notNull": true
        },
        "period_start": {
          "name": "period_start",
          "type": "timestamp",
          "primaryKey": false,
          "notNull": true
        },
        "period_end": {
          "name": "period_end",
          "type": "timestamp",
          "primaryKey": false,
          "notNull": true
        },
        "total_amount": {
          "name": "total_amount",
          "type": "numeric(10, 2)",
          "primaryKey": false,
          "notNull": true
        },
        "currency": {
          "name": "currency",
          "type": "varchar(3)",
          "primaryKey": false,
          "notNull": true,
          "default": "'USD'"
        },
        "source_system": {
          "name": "source_system",
          "type": "invoice_source",
          "typeSchema": "public",
          "primaryKey": false,
          "notNull": true,
          "default": "'manual'"
        },
        "checksum": {
          "name": "checksum",
          "type": "varchar(64)",
          "primaryKey": false,
          "notNull": false
        },
        "pdf_data": {
          "name": "pdf_data",
          "type": "text",
          "primaryKey": false,
          "notNull": false
        },
        "pdf_url": {
          "name": "pdf_url",
          "type": "varchar(1000)",
          "primaryKey": false,
          "notNull": false
        },
        "raw_data": {
          "name": "raw_data",
          "type": "jsonb",
          "primaryKey": false,
          "notNull": false
        },
        "is_active": {
          "name": "is_active",
          "type": "boolean",
          "primaryKey": false,
          "notNull": true,
          "default": true
        },
        "created_at": {
          "name": "created_at",
          "type": "timestamp",
          "primaryKey": false,
          "notNull": true,
          "default": "now()"
        },
        "deleted_at": {
          "name": "deleted_at",
          "type": "timestamp",
          "primaryKey": false,
          "notNull": false
        }
      },
      "indexes": {
        "idx_invoices_platform_period": {
          "name": "idx_invoices_platform_period",
          "columns": [
            {
              "expression": "platform_id",
              "isExpression": false,
              "asc": true,
              "nulls": "last"
            },
            {
              "expression": "period_start",
              "isExpression": false,
              "asc": true,
              "nulls": "last"
            }
          ],
          "isUnique": false,
          "concurrently": false,
          "method": "btree",
          "with": {}
        },
        "idx_invoices_checksum": {
          "name": "idx_invoices_checksum",
          "columns": [
            {
              "expression": "checksum",
              "isExpression": false,
              "asc": true,
              "nulls": "last"
            }
          ],
          "isUnique": false,
          "concurrently": false,
          "method": "btree",
          "with": {}
        }
      },
      "foreignKeys": {
        "invoices_platform_id_platforms_id_fk": {
          "name": "invoices_platform_id_platforms_id_fk",
          "tableFrom": "invoices",
          "tableTo": "platforms",
          "columnsFrom": [
            "platform_id"
          ],
          "columnsTo": [
            "id"
          ],
          "onDelete": "no action",
          "onUpdate": "no action"
        }
      },
      "compositePrimaryKeys": {},
      "uniqueConstraints": {},
      "policies": {},
      "checkConstraints": {},
      "isRLSEnabled": false
    },
    "public.optimizations": {
      "name": "optimizations",
      "schema": "",
      "columns": {
        "id": {
          "name": "id",
          "type": "integer",
          "primaryKey": true,
          "notNull": true,
          "identity": {
            "type": "always",
            "name": "optimizations_id_seq",
            "schema": "public",
            "increment": "1",
            "startWith": "1",
            "minValue": "1",
            "maxValue": "2147483647",
            "cache": "1",
            "cycle": false
          }
        },
        "title": {
          "name": "title",
          "type": "varchar(255)",
          "primaryKey": false,
          "notNull": true
        },
        "description": {
          "name": "description",
          "type": "text",
          "primaryKey": false,
          "notNull": true
        },
        "platform_id": {
          "name": "platform_id",
          "type": "integer",
          "primaryKey": false,
          "notNull": false
        },
        "service_id": {
          "name": "service_id",
          "type": "integer",
          "primaryKey": false,
          "notNull": false
        },
        "estimated_savings": {
          "name": "estimated_savings",
          "type": "numeric(10, 2)",
          "primaryKey": false,
          "notNull": false
        },
        "effort": {
          "name": "effort",
          "type": "effort",
          "typeSchema": "public",
          "primaryKey": false,
          "notNull": true,
          "default": "'medium'"
        },
        "status": {
          "name": "status",
          "type": "optimization_status",
          "typeSchema": "public",
          "primaryKey": false,
          "notNull": true,
          "default": "'suggested'"
        },
        "suggested_by": {
          "name": "suggested_by",
          "type": "actor_type",
          "typeSchema": "public",
          "primaryKey": false,
          "notNull": true,
          "default": "'ai'"
        },
        "approved_at": {
          "name": "approved_at",
          "type": "timestamp",
          "primaryKey": false,
          "notNull": false
        },
        "implemented_at": {
          "name": "implemented_at",
          "type": "timestamp",
          "primaryKey": false,
          "notNull": false
        },
        "is_active": {
          "name": "is_active",
          "type": "boolean",
          "primaryKey": false,
          "notNull": true,
          "default": true
        },
        "created_at": {
          "name": "created_at",
          "type": "timestamp",
          "primaryKey": false,
          "notNull": true,
          "default": "now()"
        },
        "deleted_at": {
          "name": "deleted_at",
          "type": "timestamp",
          "primaryKey": false,
          "notNull": false
        }
      },
      "indexes": {},
      "foreignKeys": {
        "optimizations_platform_id_platforms_id_fk": {
          "name": "optimizations_platform_id_platforms_id_fk",
          "tableFrom": "optimizations",
          "tableTo": "platforms",
          "columnsFrom": [
            "platform_id"
          ],
          "columnsTo": [
            "id"
          ],
          "onDelete": "no action",
          "onUpdate": "no action"
        },
        "optimizations_service_id_services_id_fk": {
          "name": "optimizations_service_id_services_id_fk",
          "tableFrom": "optimizations",
          "tableTo": "services",
          "columnsFrom": [
            "service_id"
          ],
          "columnsTo": [
            "id"
          ],
          "onDelete": "no action",
          "onUpdate": "no action"
        }
      },
      "compositePrimaryKeys": {},
      "uniqueConstraints": {},
      "policies": {},
      "checkConstraints": {},
      "isRLSEnabled": false
    },
    "public.platforms": {
      "name": "platforms",
      "schema": "",
      "columns": {
        "id": {
          "name": "id",
          "type": "integer",
          "primaryKey": true,
          "notNull": true,
          "identity": {
            "type": "always",
            "name": "platforms_id_seq",
            "schema": "public",
            "increment": "1",
            "startWith": "1",
            "minValue": "1",
            "maxValue": "2147483647",
            "cache": "1",
            "cycle": false
          }
        },
        "slug": {
          "name": "slug",
          "type": "varchar(50)",
          "primaryKey": false,
          "notNull": true
        },
        "name": {
          "name": "name",
          "type": "varchar(100)",
          "primaryKey": false,
          "notNull": true
        },
        "type": {
          "name": "type",
          "type": "varchar(50)",
          "primaryKey": false,
          "notNull": true
        },
        "collection_method": {
          "name": "collection_method",
          "type": "collection_method",
          "typeSchema": "public",
          "primaryKey": false,
          "notNull": true,
          "default": "'manual'"
        },
        "billing_cycle": {
          "name": "billing_cycle",
          "type": "varchar(20)",
          "primaryKey": false,
          "notNull": true,
          "default": "'monthly'"
        },
        "account_identifier": {
          "name": "account_identifier",
          "type": "varchar(255)",
          "primaryKey": false,
          "notNull": false
        },
        "api_config_key": {
          "name": "api_config_key",
          "type": "varchar(100)",
          "primaryKey": false,
          "notNull": false
        },
        "is_active": {
          "name": "is_active",
          "type": "boolean",
          "primaryKey": false,
          "notNull": true,
          "default": true
        },
        "created_at": {
          "name": "created_at",
          "type": "timestamp",
          "primaryKey": false,
          "notNull": true,
          "default": "now()"
        },
        "deleted_at": {
          "name": "deleted_at",
          "type": "timestamp",
          "primaryKey": false,
          "notNull": false
        }
      },
      "indexes": {},
      "foreignKeys": {},
      "compositePrimaryKeys": {},
      "uniqueConstraints": {
        "platforms_slug_unique": {
          "name": "platforms_slug_unique",
          "nullsNotDistinct": false,
          "columns": [
            "slug"
          ]
        }
      },
      "policies": {},
      "checkConstraints": {},
      "isRLSEnabled": false
    },
    "public.projects": {
      "name": "projects",
      "schema": "",
      "columns": {
        "id": {
          "name": "id",
          "type": "integer",
          "primaryKey": true,
          "notNull": true,
          "identity": {
            "type": "always",
            "name": "projects_id_seq",
            "schema": "public",
            "increment": "1",
            "startWith": "1",
            "minValue": "1",
            "maxValue": "2147483647",
            "cache": "1",
            "cycle": false
          }
        },
        "slug": {
          "name": "slug",
          "type": "varchar(100)",
          "primaryKey": false,
          "notNull": true
        },
        "name": {
          "name": "name",
          "type": "varchar(255)",
          "primaryKey": false,
          "notNull": true
        },
        "description": {
          "name": "description",
          "type": "text",
          "primaryKey": false,
          "notNull": false
        },
        "repo_url": {
          "name": "repo_url",
          "type": "varchar(500)",
          "primaryKey": false,
          "notNull": false
        },
        "production_url": {
          "name": "production_url",
          "type": "varchar(500)",
          "primaryKey": false,
          "notNull": false
        },
        "tech_stack": {
          "name": "tech_stack",
          "type": "jsonb",
          "primaryKey": false,
          "notNull": false
        },
        "status": {
          "name": "status",
          "type": "project_status",
          "typeSchema": "public",
          "primaryKey": false,
          "notNull": true,
          "default": "'active'"
        },
        "monthly_budget": {
          "name": "monthly_budget",
          "type": "numeric(10, 2)",
          "primaryKey": false,
          "notNull": false
        },
        "discovered_at": {
          "name": "discovered_at",
          "type": "timestamp",
          "primaryKey": false,
          "notNull": true,
          "default": "now()"
        },
        "is_active": {
          "name": "is_active",
          "type": "boolean",
          "primaryKey": false,
          "notNull": true,
          "default": true
        },
        "created_at": {
          "name": "created_at",
          "type": "timestamp",
          "primaryKey": false,
          "notNull": true,
          "default": "now()"
        },
        "deleted_at": {
          "name": "deleted_at",
          "type": "timestamp",
          "primaryKey": false,
          "notNull": false
        }
      },
      "indexes": {},
      "foreignKeys": {},
      "compositePrimaryKeys": {},
      "uniqueConstraints": {
        "projects_slug_unique": {
          "name": "projects_slug_unique",
          "nullsNotDistinct": false,
          "columns": [
            "slug"
          ]
        }
      },
      "policies": {},
      "checkConstraints": {},
      "isRLSEnabled": false
    },
    "public.reconciliation_runs": {
      "name": "reconciliation_runs",
      "schema": "",
      "columns": {
        "id": {
          "name": "id",
          "type": "integer",
          "primaryKey": true,
          "notNull": true,
          "identity": {
            "type": "always",
            "name": "reconciliation_runs_id_seq",
            "schema": "public",
            "increment": "1",
            "startWith": "1",
            "minValue": "1",
            "maxValue": "2147483647",
            "cache": "1",
            "cycle": false
          }
        },
        "year": {
          "name": "year",
          "type": "integer",
          "primaryKey": false,
          "notNull": true
        },
        "month": {
          "name": "month",
          "type": "integer",
          "primaryKey": false,
          "notNull": true
        },
        "platform_id": {
          "name": "platform_id",
          "type": "integer",
          "primaryKey": false,
          "notNull": true
        },
        "cost_records_sum": {
          "name": "cost_records_sum",
          "type": "numeric(10, 4)",
          "primaryKey": false,
          "notNull": true
        },
        "invoices_sum": {
          "name": "invoices_sum",
          "type": "numeric(10, 4)",
          "primaryKey": false,
          "notNull": true
        },
        "delta": {
          "name": "delta",
          "type": "numeric(10, 4)",
          "primaryKey": false,
          "notNull": true
        },
        "delta_pct": {
          "name": "delta_pct",
          "type": "numeric(8, 4)",
          "primaryKey": false,
          "notNull": false
        },
        "status": {
          "name": "status",
          "type": "reconciliation_status",
          "typeSchema": "public",
          "primaryKey": false,
          "notNull": true
        },
        "run_at": {
          "name": "run_at",
          "type": "timestamp",
          "primaryKey": false,
          "notNull": true,
          "default": "now()"
        }
      },
      "indexes": {
        "idx_recon_platform_period": {
          "name": "idx_recon_platform_period",
          "columns": [
            {
              "expression": "platform_id",
              "isExpression": false,
              "asc": true,
              "nulls": "last"
            },
            {
              "expression": "year",
              "isExpression": false,
              "asc": true,
              "nulls": "last"
            },
            {
              "expression": "month",
              "isExpression": false,
              "asc": true,
              "nulls": "last"
            }
          ],
          "isUnique": false,
          "concurrently": false,
          "method": "btree",
          "with": {}
        }
      },
      "foreignKeys": {
        "reconciliation_runs_platform_id_platforms_id_fk": {
          "name": "reconciliation_runs_platform_id_platforms_id_fk",
          "tableFrom": "reconciliation_runs",
          "tableTo": "platforms",
          "columnsFrom": [
            "platform_id"
          ],
          "columnsTo": [
            "id"
          ],
          "onDelete": "no action",
          "onUpdate": "no action"
        }
      },
      "compositePrimaryKeys": {},
      "uniqueConstraints": {},
      "policies": {},
      "checkConstraints": {},
      "isRLSEnabled": false
    },
    "public.services": {
      "name": "services",
      "schema": "",
      "columns": {
        "id": {
          "name": "id",
          "type": "integer",
          "primaryKey": true,
          "notNull": true,
          "identity": {
            "type": "always",
            "name": "services_id_seq",
            "schema": "public",
            "increment": "1",
            "startWith": "1",
            "minValue": "1",
            "maxValue": "2147483647",
            "cache": "1",
            "cycle": false
          }
        },
        "platform_id": {
          "name": "platform_id",
          "type": "integer",
          "primaryKey": false,
          "notNull": true
        },
        "external_id": {
          "name": "external_id",
          "type": "varchar(255)",
          "primaryKey": false,
          "notNull": false
        },
        "name": {
          "name": "name",
          "type": "varchar(255)",
          "primaryKey": false,
          "notNull": true
        },
        "project": {
          "name": "project",
          "type": "varchar(100)",
          "primaryKey": false,
          "notNull": false
        },
        "service_type": {
          "name": "service_type",
          "type": "varchar(50)",
          "primaryKey": false,
          "notNull": true
        },
        "monthly_cost_estimate": {
          "name": "monthly_cost_estimate",
          "type": "numeric(10, 2)",
          "primaryKey": false,
          "notNull": false
        },
        "metadata": {
          "name": "metadata",
          "type": "jsonb",
          "primaryKey": false,
          "notNull": false
        },
        "is_active": {
          "name": "is_active",
          "type": "boolean",
          "primaryKey": false,
          "notNull": true,
          "default": true
        },
        "created_at": {
          "name": "created_at",
          "type": "timestamp",
          "primaryKey": false,
          "notNull": true,
          "default": "now()"
        },
        "deleted_at": {
          "name": "deleted_at",
          "type": "timestamp",
          "primaryKey": false,
          "notNull": false
        }
      },
      "indexes": {
        "idx_services_platform": {
          "name": "idx_services_platform",
          "columns": [
            {
              "expression": "platform_id",
              "isExpression": false,
              "asc": true,
              "nulls": "last"
            }
          ],
          "isUnique": false,
          "concurrently": false,
          "method": "btree",
          "with": {}
        },
        "idx_services_project": {
          "name": "idx_services_project",
          "columns": [
            {
              "expression": "project",
              "isExpression": false,
              "asc": true,
              "nulls": "last"
            }
          ],
          "isUnique": false,
          "concurrently": false,
          "method": "btree",
          "with": {}
        }
      },
      "foreignKeys": {
        "services_platform_id_platforms_id_fk": {
          "name": "services_platform_id_platforms_id_fk",
          "tableFrom": "services",
          "tableTo": "platforms",
          "columnsFrom": [
            "platform_id"
          ],
          "columnsTo": [
            "id"
          ],
          "onDelete": "no action",
          "onUpdate": "no action"
        }
      },
      "compositePrimaryKeys": {},
      "uniqueConstraints": {},
      "policies": {},
      "checkConstraints": {},
      "isRLSEnabled": false
    },
    "public.verifications": {
      "name": "verifications",
      "schema": "",
      "columns": {
        "id": {
          "name": "id",
          "type": "integer",
          "primaryKey": true,
          "notNull": true,
          "identity": {
            "type": "always",
            "name": "verifications_id_seq",
            "schema": "public",
            "increment": "1",
            "startWith": "1",
            "minValue": "1",
            "maxValue": "2147483647",
            "cache": "1",
            "cycle": false
          }
        },
        "platform_id": {
          "name": "platform_id",
          "type": "integer",
          "primaryKey": false,
          "notNull": true
        },
        "period_start": {
          "name": "period_start",
          "type": "timestamp",
          "primaryKey": false,
          "notNull": true
        },
        "period_end": {
          "name": "period_end",
          "type": "timestamp",
          "primaryKey": false,
          "notNull": true
        },
        "reported_usd": {
          "name": "reported_usd",
          "type": "numeric(10, 4)",
          "primaryKey": false,
          "notNull": true
        },
        "verified_usd": {
          "name": "verified_usd",
          "type": "numeric(10, 4)",
          "primaryKey": false,
          "notNull": true
        },
        "delta": {
          "name": "delta",
          "type": "numeric(10, 4)",
          "primaryKey": false,
          "notNull": true
        },
        "delta_pct": {
          "name": "delta_pct",
          "type": "numeric(8, 4)",
          "primaryKey": false,
          "notNull": false
        },
        "method": {
          "name": "method",
          "type": "verification_method",
          "typeSchema": "public",
          "primaryKey": false,
          "notNull": true,
          "default": "'manual'"
        },
        "notes": {
          "name": "notes",
          "type": "jsonb",
          "primaryKey": false,
          "notNull": false
        },
        "verified_at": {
          "name": "verified_at",
          "type": "timestamp",
          "primaryKey": false,
          "notNull": true,
          "default": "now()"
        },
        "verified_by": {
          "name": "verified_by",
          "type": "varchar(100)",
          "primaryKey": false,
          "notNull": true,
          "default": "'peter'"
        },
        "is_active": {
          "name": "is_active",
          "type": "boolean",
          "primaryKey": false,
          "notNull": true,
          "default": true
        },
        "created_at": {
          "name": "created_at",
          "type": "timestamp",
          "primaryKey": false,
          "notNull": true,
          "default": "now()"
        }
      },
      "indexes": {
        "idx_verifications_platform_period": {
          "name": "idx_verifications_platform_period",
          "columns": [
            {
              "expression": "platform_id",
              "isExpression": false,
              "asc": true,
              "nulls": "last"
            },
            {
              "expression": "period_start",
              "isExpression": false,
              "asc": true,
              "nulls": "last"
            }
          ],
          "isUnique": false,
          "concurrently": false,
          "method": "btree",
          "with": {}
        }
      },
      "foreignKeys": {
        "verifications_platform_id_platforms_id_fk": {
          "name": "verifications_platform_id_platforms_id_fk",
          "tableFrom": "verifications",
          "tableTo": "platforms",
          "columnsFrom": [
            "platform_id"
          ],
          "columnsTo": [
            "id"
          ],
          "onDelete": "no action",
          "onUpdate": "no action"
        }
      },
      "compositePrimaryKeys": {},
      "uniqueConstraints": {},
      "policies": {},
      "checkConstraints": {},
      "isRLSEnabled": false
    }
  },
  "enums": {
    "public.actor_type": {
      "name": "actor_type",
      "schema": "public",
      "values": [
        "system",
        "user",
        "ai"
      ]
    },
    "public.alert_severity": {
      "name": "alert_severity",
      "schema": "public",
      "values": [
        "info",
        "warning",
        "critical"
      ]
    },
    "public.alert_status": {
      "name": "alert_status",
      "schema": "public",
      "values": [
        "pending",
        "sent",
        "acknowledged",
        "resolved"
      ]
    },
    "public.collection_method": {
      "name": "collection_method",
      "schema": "public",
      "values": [
        "api",
        "hybrid",
        "manual",
        "csv_import"
      ]
    },
    "public.collection_run_status": {
      "name": "collection_run_status",
      "schema": "public",
      "values": [
        "running",
        "success",
        "partial",
        "failed"
      ]
    },
    "public.cost_type": {
      "name": "cost_type",
      "schema": "public",
      "values": [
        "subscription",
        "usage",
        "overage",
        "one_time"
      ]
    },
    "public.effort": {
      "name": "effort",
      "schema": "public",
      "values": [
        "trivial",
        "small",
        "medium",
        "large"
      ]
    },
    "public.invoice_source": {
      "name": "invoice_source",
      "schema": "public",
      "values": [
        "platform_api",
        "email_parse",
        "manual"
      ]
    },
    "public.optimization_status": {
      "name": "optimization_status",
      "schema": "public",
      "values": [
        "suggested",
        "approved",
        "rejected",
        "implemented",
        "dismissed"
      ]
    },
    "public.project_status": {
      "name": "project_status",
      "schema": "public",
      "values": [
        "active",
        "paused",
        "archived"
      ]
    },
    "public.reconciliation_status": {
      "name": "reconciliation_status",
      "schema": "public",
      "values": [
        "match",
        "over",
        "under",
        "no_invoice",
        "no_records"
      ]
    },
    "public.verification_method": {
      "name": "verification_method",
      "schema": "public",
      "values": [
        "manual",
        "browser",
        "cli",
        "api"
      ]
    }
  },
  "schemas": {},
  "sequences": {},
  "roles": {},
  "policies": {},
  "views": {},
  "_meta": {
    "columns": {},
    "schemas": {},
    "tables": {}
  }
}